tolstoy_agents/__init__.py
tolstoy_agents/dynamo_db_session_history.py
tolstoy_agents/gemini_client.py
tolstoy_agents/google_spreadsheet.py
tolstoy_agents/linear.py
tolstoy_agents/utils.py
tolstoy_agents/agents/__init__.py
tolstoy_agents/agents/agent_with_structured_output.py
tolstoy_agents/agents/worker_graph.py
tolstoy_agents/executors/__init__.py
tolstoy_agents/executors/executor.py
tolstoy_agents/retrievers/__init__.py
tolstoy_agents/retrievers/adaptive_rag.py
tolstoy_agents/retrievers/utils.py
tolstoy_agents/roles/__init__.py
tolstoy_agents/roles/customer_success_manager.py
tolstoy_agents/roles/responder.py
tolstoy_agents/roles/reviewer.py
tolstoy_agents/roles/role.py
tolstoy_agents/roles/task_agent.py
tolstoy_agents/tools/__init__.py
tolstoy_agents/tools/analyze_loom_video_tool.py
tolstoy_agents/tools/comment_linear_issue_tool.py
tolstoy_agents/tools/fetch_web_content_tool.py
tolstoy_agents/tools/get_cs_review_state_tool.py
tolstoy_agents/tools/get_meeting_links_tool.py
tolstoy_agents/tools/human_as_a_tool.py
tolstoy_agents/tools/product_kb_tool.py
tolstoy_agents/tools/query_linear_issue_tool.py
tolstoy_agents/tools/support_human_tool.py
tolstoy_agents/tools/web_base_loader.py
tolstoy_agents/tools/web_content_retriever_tool.py
tolstoy_agents/tools/web_search_tool.py
tolstoy_agents-0.1.51.dist-info/LICENSE
tolstoy_agents-0.1.51.dist-info/METADATA
tolstoy_agents-0.1.51.dist-info/WHEEL
tolstoy_agents-0.1.51.dist-info/top_level.txt
tolstoy_agents-0.1.51.dist-info/RECORD
