Metadata-Version: 2.1
Name: tolstoy-agents
Version: 0.1.51
Summary: Framework to create LLM agents
Home-page: UNKNOWN
Author: Tolstoy
Author-email: tolstoy@gotolstoy.com
License: UNKNOWN
Platform: UNKNOWN
Classifier: Programming Language :: Python :: 3
Classifier: License :: OSI Approved :: MIT License
Classifier: Operating System :: OS Independent
Requires-Python: >=3.6
Requires-Dist: langgraph<0.3.0,>=0.2.16
Requires-Dist: langchain<0.4.0,>=0.2.15
Requires-Dist: langchain-openai<0.4.0,>=0.1.23
Requires-Dist: langchain-core<0.4.0,>=0.2.35
Requires-Dist: langchain-community<0.3.0,>=0.2.16
